README.md
setup.py
nsg_orca.egg-info/PKG-INFO
nsg_orca.egg-info/SOURCES.txt
nsg_orca.egg-info/dependency_links.txt
nsg_orca.egg-info/top_level.txt
orca_module/__init__.py
orca_module/orca.py