Metadata-Version: 1.0
Name: nsg-orca
Version: 0.0.2
Summary: A module to interact with NSG Orca data
Home-page: UNKNOWN
Author: Zach Bray, Vecheka Chhourn
Author-email: Zachary.Bray@nordstrom.com, Vecheka.Chhourn@nordstrom.com
License: MIT
Keywords: Orca,orca,orca_module,nsg-orca
Platform: UNKNOWN
